st_aggrid_community/__init__.py
st_aggrid_community/frontend/.env
st_aggrid_community/frontend/.prettierrc
st_aggrid_community/frontend/package.json
st_aggrid_community/frontend/public/bootstrap.min.css
st_aggrid_community/frontend/public/index.html
st_aggrid_community/frontend/tsconfig.json
st_aggrid_community/grid_options_builder.py
st_aggrid_community/shared.py
streamlit_aggrid_community-0.3.4.dist-info/LICENSE
streamlit_aggrid_community-0.3.4.dist-info/WHEEL
streamlit_aggrid_community-0.3.4.dist-info/METADATA
streamlit_aggrid_community-0.3.4.dist-info/RECORD
