Metadata-Version: 2.1
Name: streamlit-aggrid-community
Version: 0.3.4
Summary: Streamlit component implementation of ag-grid
Home-page: https://github.com/LucasTrg/streamlit-aggrid-community
Author: Pablo Fonseca
Author-email: pablo.fonseca+pip@gmail.com
Requires-Python: >=3.7.8,<4.0
Classifier: License :: OSI Approved :: MIT License
Classifier: Operating System :: OS Independent
Classifier: Programming Language :: Python :: 3
Classifier: Programming Language :: Python :: 3.10
Classifier: Programming Language :: Python :: 3.8
Classifier: Programming Language :: Python :: 3.9
Requires-Dist: pandas (>=1.2)
Requires-Dist: python-decouple (>=3.6,<4.0)
Requires-Dist: streamlit (>=0.87.0)
